DjangoDbNotesAsync/__init__.py
DjangoDbNotesAsync/management/__init__.py
DjangoDbNotesAsync/management/commands/__init__.py
DjangoDbNotesAsync/management/commands/db_notes_async.py
DjangoDbNotesAsync-1.0.2.dist-info/METADATA
DjangoDbNotesAsync-1.0.2.dist-info/RECORD
DjangoDbNotesAsync-1.0.2.dist-info/WHEEL
DjangoDbNotesAsync-1.0.2.dist-info/top_level.txt
