Metadata-Version: 2.1
Name: DjangoDbNotesAsync
Version: 1.0.2
Summary: a package for adding django model notes and field help_text to mysql table comment and field comment
Home-page: https://github.com/yirantai-Angle/DjangoDbNotesAsync
Author: yirantai
Author-email: 896275756@qq.com
License: UNKNOWN
Platform: UNKNOWN
Classifier: Programming Language :: Python :: 3.6
Classifier: License :: OSI Approved :: MIT License
Classifier: Operating System :: OS Independent
